[
{"username":"Svein T veitdal","id":"75742264","followers":"173714"},
{"username":"Katrina vandenHeuvel","id":"59159771","followers":"140970"},
{"username":"Thom Hartmann","id":"21414576","followers":"63294"},
{"username":"Vitor Santos","id":"113410319","followers":"28057"},
{"username":"FREE socially","id":"533665109","followers":"26306"},
{"username":"Conform Comics","id":"2891477268","followers":"18637"},
{"username":"Andrew Winston","id":"33955377","followers":"17425"},
{"username":"Marjan Minnesma","id":"198514243","followers":"14085"},
{"username":"A Travel American","id":"520572849","followers":"13725"},
{"username":"Olav Kjorven","id":"30324031","followers":"13292"},
{"username":"Jeanne Blake","id":"33578917","followers":"11965"},
{"username":"ISC","id":"20703527","followers":"10822"},
{"username":"AMC","id":"124898913","followers":"10372"},
{"username":"#BoycottKoch","id":"1571317760","followers":"10284"},
{"username":"#BoycottKoch","id":"1571317760","followers":"10284"},
{"username":"Andreas Eligium","id":"547839306","followers":"9999"},
{"username":"Kevindoylejones","id":"16481668","followers":"9552"},
{"username":"The Daily Planet","id":"1723563360","followers":"8584"},
{"username":"Mark Sleboda","id":"1813434864","followers":"7442"},
{"username":"paleBLUEdot","id":"2680015243","followers":"7394"},
{"username":"heyNSA Get A Warrant","id":"415826305","followers":"7294"},
{"username":"Marc Slavin","id":"2516013102","followers":"7171"},
{"username":"JaneyHowe","id":"1208242926","followers":"6264"},
{"username":"Hollywood Food Guild","id":"3124211590","followers":"6186"},
{"username":"ClimateWarrior2015","id":"3056468552","followers":"6123"},
{"username":"ClimateWarrior2015","id":"3056468552","followers":"6123"},
{"username":"Travels #4Charity","id":"518873929","followers":"5840"},
{"username":"Dave","id":"260724365","followers":"5832"},
{"username":"Match Made in Heaven","id":"522740741","followers":"5767"},
{"username":"Match Made in Heaven","id":"522740741","followers":"5767"},
{"username":"Cagan H. Sekercioglu","id":"66558585","followers":"4790"},
{"username":"Anders Wijkman","id":"620396271","followers":"4780"},
{"username":"Michelle","id":"2475599276","followers":"4371"},
{"username":"JerryO'Donnell","id":"42741261","followers":"4216"},
{"username":"NewZealandEconomics","id":"28719383","followers":"3958"},
{"username":"Tundra Gear","id":"12108252","followers":"3810"},
{"username":"Graham Scambler","id":"617029017","followers":"3767"},
{"username":"Crates","id":"19992567","followers":"3435"},
{"username":"Ruth Glendinning","id":"5820872","followers":"3366"},
{"username":"och aye the news","id":"1681040568","followers":"3266"},
{"username":"Lawan Suwannarat","id":"364720450","followers":"3242"},
{"username":"Laure","id":"1164224114","followers":"3134"},
{"username":"Knut S. Rosenlund","id":"32144904","followers":"3057"},
{"username":"BHP Animal Watch","id":"169949875","followers":"2917"},
{"username":"Charity Travel Deals","id":"413434627","followers":"2703"},
{"username":"Geoffrey M Hodgson","id":"2168155795","followers":"2533"},
{"username":"The Tory Way","id":"15616667","followers":"2373"},
{"username":"kenjerakota","id":"3343738493","followers":"2300"},
{"username":"Kathleen Wattle","id":"76713592","followers":"2288"},
{"username":"Shelli","id":"21519788","followers":"2286"},
{"username":"♪Leovani Böshaar♪","id":"236004061","followers":"2267"},
{"username":"netminnow","id":"242051914","followers":"2244"},
{"username":"Anita Woodruff","id":"745848188","followers":"2224"},
{"username":"Jeremy J Nichols","id":"410462891","followers":"2208"},
{"username":"runtodaylight","id":"15332026","followers":"2208"},
{"username":"Climate Resolve","id":"312335223","followers":"2205"},
{"username":"Tracy Rue","id":"2231994344","followers":"2176"},
{"username":"Michael Rafa","id":"116296937","followers":"2161"},
{"username":"Joshua Sandernista","id":"93727830","followers":"2161"},
{"username":"Mark Lubell","id":"1694401938","followers":"2051"},
{"username":"Stop TPP","id":"3300942849","followers":"2004"},
{"username":"DeSmog UK","id":"2620095853","followers":"1957"},
{"username":"DeSmog UK","id":"2620095853","followers":"1957"},
{"username":"Sol Hog","id":"14799078","followers":"1874"},
{"username":"Lori Lalama","id":"160765446","followers":"1836"},
{"username":"justjayhere","id":"1642106527","followers":"1828"},
{"username":"random flower ^_^","id":"15471305","followers":"1822"},
{"username":"Fabius Maximus (Ed.)","id":"168708945","followers":"1798"},
{"username":"Deborah Hopkins","id":"1072356338","followers":"1704"},
{"username":"Mary St George","id":"181909635","followers":"1563"},
{"username":"Tom Schueneman","id":"14357007","followers":"1479"},
{"username":"Tom Schueneman","id":"14357007","followers":"1479"},
{"username":"Stop Racism Canada","id":"110728224","followers":"1453"},
{"username":"Semper","id":"85729788","followers":"1427"},
{"username":"Tim Riggle","id":"160089089","followers":"1409"},
{"username":"JAM","id":"629359957","followers":"1363"},
{"username":"Energy Renaissance","id":"4721574708","followers":"1304"},
{"username":"Energy Renaissance","id":"4721574708","followers":"1304"},
{"username":"Mel","id":"3308983627","followers":"1284"},
{"username":"Jim Boyle","id":"107787714","followers":"1269"},
{"username":"C-Smart Solutions","id":"4370562018","followers":"1257"},
{"username":"Green Planet Social","id":"532706651","followers":"1256"},
{"username":"Timmons Roberts","id":"375071867","followers":"1210"},
{"username":"Timmons Roberts","id":"375071867","followers":"1210"},
{"username":"GreenAct2020","id":"281916835","followers":"1208"},
{"username":"di is in los angeles","id":"17431441","followers":"1117"},
{"username":"Tom Zawacki","id":"141750152","followers":"1109"},
{"username":"Sprouting Green","id":"525361019","followers":"1106"},
{"username":"GreenAct2020 Türkiye","id":"1885716068","followers":"1104"},
{"username":"Old man in hat","id":"2545900439","followers":"1099"},
{"username":"GB","id":"161162501","followers":"1088"},
{"username":"Social Tools #4h2o","id":"572334136","followers":"1079"},
{"username":"Arun Agrawal","id":"926409020","followers":"1072"},
{"username":"Gerard","id":"439198830","followers":"1033"},
{"username":"Hannah Doress","id":"54353360","followers":"979"},
{"username":"D","id":"2610595777","followers":"968"},
{"username":"TopJob","id":"166603532","followers":"961"},
{"username":"JTerri","id":"2350842762","followers":"960"},
{"username":"Social Tools","id":"522339656","followers":"941"},
{"username":"Social Tools","id":"522339656","followers":"941"}
]